{"DocumentConnection":{"type":"DocumentConnection","resolveType":"multiCollectionDocumentList","collections":["homepage","pages","auditoria","redaccion_web","redaccion_estrategica_blogs","contact_page","sobre_mi","servicios_page","colaboraciones_agencias","renovar_web_y_blog_empresa"]},"Node":{"type":"Node","resolveType":"nodeDocument"},"DocumentNode":{"type":"DocumentNode","resolveType":"multiCollectionDocument","createDocument":"create","updateDocument":"update"},"Homepage":{"type":"Homepage","resolveType":"collectionDocument","collection":"homepage","createHomepage":"create","updateHomepage":"update"},"HomepageConnection":{"type":"HomepageConnection","resolveType":"collectionDocumentList","collection":"homepage"},"Pages":{"type":"Pages","resolveType":"collectionDocument","collection":"pages","createPages":"create","updatePages":"update"},"PagesConnection":{"type":"PagesConnection","resolveType":"collectionDocumentList","collection":"pages"},"Auditoria":{"type":"Auditoria","resolveType":"collectionDocument","collection":"auditoria","createAuditoria":"create","updateAuditoria":"update"},"AuditoriaConnection":{"type":"AuditoriaConnection","resolveType":"collectionDocumentList","collection":"auditoria"},"Redaccion_web":{"type":"Redaccion_web","resolveType":"collectionDocument","collection":"redaccion_web","createRedaccion_web":"create","updateRedaccion_web":"update"},"Redaccion_webConnection":{"type":"Redaccion_webConnection","resolveType":"collectionDocumentList","collection":"redaccion_web"},"Redaccion_estrategica_blogs":{"type":"Redaccion_estrategica_blogs","resolveType":"collectionDocument","collection":"redaccion_estrategica_blogs","createRedaccion_estrategica_blogs":"create","updateRedaccion_estrategica_blogs":"update"},"Redaccion_estrategica_blogsConnection":{"type":"Redaccion_estrategica_blogsConnection","resolveType":"collectionDocumentList","collection":"redaccion_estrategica_blogs"},"Contact_page":{"type":"Contact_page","resolveType":"collectionDocument","collection":"contact_page","createContact_page":"create","updateContact_page":"update"},"Contact_pageConnection":{"type":"Contact_pageConnection","resolveType":"collectionDocumentList","collection":"contact_page"},"Sobre_mi":{"type":"Sobre_mi","resolveType":"collectionDocument","collection":"sobre_mi","createSobre_mi":"create","updateSobre_mi":"update"},"Sobre_miConnection":{"type":"Sobre_miConnection","resolveType":"collectionDocumentList","collection":"sobre_mi"},"Servicios_page":{"type":"Servicios_page","resolveType":"collectionDocument","collection":"servicios_page","createServicios_page":"create","updateServicios_page":"update"},"Servicios_pageConnection":{"type":"Servicios_pageConnection","resolveType":"collectionDocumentList","collection":"servicios_page"},"Colaboraciones_agencias":{"type":"Colaboraciones_agencias","resolveType":"collectionDocument","collection":"colaboraciones_agencias","createColaboraciones_agencias":"create","updateColaboraciones_agencias":"update"},"Colaboraciones_agenciasConnection":{"type":"Colaboraciones_agenciasConnection","resolveType":"collectionDocumentList","collection":"colaboraciones_agencias"},"Renovar_web_y_blog_empresa":{"type":"Renovar_web_y_blog_empresa","resolveType":"collectionDocument","collection":"renovar_web_y_blog_empresa","createRenovar_web_y_blog_empresa":"create","updateRenovar_web_y_blog_empresa":"update"},"Renovar_web_y_blog_empresaConnection":{"type":"Renovar_web_y_blog_empresaConnection","resolveType":"collectionDocumentList","collection":"renovar_web_y_blog_empresa"}}